new_celery_config/__init__.py
new_celery_config/as_module.py
new_celery_config-0.2.0.dist-info/LICENSE
new_celery_config-0.2.0.dist-info/WHEEL
new_celery_config-0.2.0.dist-info/METADATA
new_celery_config-0.2.0.dist-info/RECORD
