Metadata-Version: 2.1
Name: new-celery-config
Version: 0.2.0
Summary: new-celery-config specifies Celery configuration via environment variables.
Home-page: https://github.com/neocrym/new-celery-config
License: MIT
Author: Neocrym Records Inc.
Author-email: engineering@neocrym.com
Requires-Python: >=3.8,<4.0
Classifier: License :: OSI Approved :: MIT License
Classifier: Programming Language :: Python :: 3
Classifier: Programming Language :: Python :: 3.10
Classifier: Programming Language :: Python :: 3.8
Classifier: Programming Language :: Python :: 3.9
Classifier: Topic :: Software Development :: Object Brokering
Classifier: Topic :: System :: Distributed Computing
Requires-Dist: PyYAML
Project-URL: Repository, https://github.com/neocrym/new-celery-config
